hivejdbc/__init__.py
hivejdbc/types.py
hivejdbc-0.2.3.dist-info/LICENSE
hivejdbc-0.2.3.dist-info/METADATA
hivejdbc-0.2.3.dist-info/WHEEL
hivejdbc-0.2.3.dist-info/top_level.txt
hivejdbc-0.2.3.dist-info/RECORD
