Metadata-Version: 2.1
Name: hivejdbc
Version: 0.2.3
Summary: Hive database driver via jdbc
Home-page: https://github.com/OpenBigDataPlatform/hivejdbc
Author: OpenBigDataPlatform
License: Apache-2.0
Keywords: dbapi jdbc hive hadoop
Platform: UNKNOWN
Classifier: Development Status :: 4 - Beta
Classifier: Intended Audience :: Developers
Classifier: Programming Language :: Java
Classifier: Programming Language :: Python :: 3
Classifier: Topic :: Database
Classifier: Topic :: Software Development :: Libraries :: Java Libraries
Classifier: Topic :: Software Development :: Libraries :: Python Modules
Requires-Dist: pyjdbc (==0.2.2)
